scCCA/__init__.py
scCCA/cca.py
scCCA/logger.py
scCCA/model.py
scCCA/pca.py
scCCA/plots/__init__.py
scCCA/plots/factor_embedding.py
scCCA/plots/loadings_bar.py
scCCA/plots/loadings_scatter.py
scCCA/plots/qc.py
scCCA/plots/utils.py
scCCA/train/__init__.py
scCCA/train/handler.py
scCCA/train/local_handler.py
scCCA/train/settings.py
scCCA/utils/__init__.py
scCCA/utils/data.py
scCCA/utils/design.py
scCCA/utils/scanpy.py
sccca-0.3.1.dist-info/WHEEL
sccca-0.3.1.dist-info/METADATA
sccca-0.3.1.dist-info/RECORD
